basalam.backbone_translation-1.0.1-py3.12-nspkg.pth
basalam/backbone_translation/__init__.py
basalam/backbone_translation/translator.py
basalam.backbone_translation-1.0.1.dist-info/LICENSE
basalam.backbone_translation-1.0.1.dist-info/METADATA
basalam.backbone_translation-1.0.1.dist-info/WHEEL
basalam.backbone_translation-1.0.1.dist-info/namespace_packages.txt
basalam.backbone_translation-1.0.1.dist-info/top_level.txt
basalam.backbone_translation-1.0.1.dist-info/RECORD
